jmcomic/__init__.py
jmcomic/api.py
jmcomic/cl.py
jmcomic/jm_client_impl.py
jmcomic/jm_client_interface.py
jmcomic/jm_config.py
jmcomic/jm_downloader.py
jmcomic/jm_entity.py
jmcomic/jm_exception.py
jmcomic/jm_option.py
jmcomic/jm_plugin.py
jmcomic/jm_toolkit.py
jmcomic-2.6.12.dist-info/licenses/LICENSE
jmcomic-2.6.12.dist-info/METADATA
jmcomic-2.6.12.dist-info/WHEEL
jmcomic-2.6.12.dist-info/entry_points.txt
jmcomic-2.6.12.dist-info/top_level.txt
jmcomic-2.6.12.dist-info/RECORD
