Metadata-Version: 2.4
Name: jmcomic
Version: 2.6.12
Summary: Python API For JMComic (禁漫天堂)
Home-page: https://github.com/hect0x7/JMComic-Crawler-Python
Author: hect0x7
Author-email: hect0x7 <93357912+hect0x7@users.noreply.github.com>
License: MIT License
Project-URL: Homepage, https://github.com/hect0x7/JMComic-Crawler-Python
Project-URL: Documentation, https://jmcomic.readthedocs.io
Keywords: python,jmcomic,18comic,禁漫天堂,NSFW
Classifier: Development Status :: 4 - Beta
Classifier: License :: OSI Approved :: MIT License
Classifier: Intended Audience :: Developers
Classifier: Programming Language :: Python :: 3.7
Classifier: Programming Language :: Python :: 3.8
Classifier: Programming Language :: Python :: 3.9
Classifier: Programming Language :: Python :: 3.10
Classifier: Programming Language :: Python :: 3.11
Classifier: Programming Language :: Python :: 3.12
Classifier: Programming Language :: Python :: 3.13
Classifier: Operating System :: MacOS
Classifier: Operating System :: POSIX :: Linux
Classifier: Operating System :: Microsoft :: Windows
Requires-Python: >=3.7
License-File: LICENSE
Requires-Dist: commonx>=0.6.38
Requires-Dist: curl-cffi
Requires-Dist: pillow
Requires-Dist: pycryptodome
Requires-Dist: pyyaml
Dynamic: author
Dynamic: home-page
Dynamic: license-file
Dynamic: requires-python
